{"./":{"url":"./","title":"Introduction","keywords":"","body":"前言 "},"test1/test1.html":{"url":"test1/test1.html","title":"Test1","keywords":"","body":"这是test1 这是内容1 "},"test1/test2.html":{"url":"test1/test2.html","title":"Test2","keywords":"","body":"test1 中的 test2 "},"test1/test3.html":{"url":"test1/test3.html","title":"Test3","keywords":"","body":"test1 中的 test3 "},"test2/test2-1/test2-1-1.html":{"url":"test2/test2-1/test2-1-1.html","title":"Test2 1 1","keywords":"","body":"test2-1-1 "},"test2/test2-1/test2-1-2.html":{"url":"test2/test2-1/test2-1-2.html","title":"Test2 1 2","keywords":"","body":"搜索 "},"test2/test2.html":{"url":"test2/test2.html","title":"Test2","keywords":"","body":"这是test2 这是内容2 "},"测试中文/test.html":{"url":"测试中文/test.html","title":"Test","keywords":"","body":"中文 "},"测试中文/测试中文.html":{"url":"测试中文/测试中文.html","title":"测试中文","keywords":"","body":"测试中文 "}}